quadproj/__init__.py
quadproj/fun.py
quadproj/project.py
quadproj/quadrics.py
quadproj/utils.py
quadproj-2.1.0.dist-info/LICENSE
quadproj-2.1.0.dist-info/METADATA
quadproj-2.1.0.dist-info/WHEEL
quadproj-2.1.0.dist-info/top_level.txt
quadproj-2.1.0.dist-info/RECORD
