Metadata-Version: 2.1
Name: quadproj
Version: 2.1.0
Summary: A package to project onto quadratic hypersurfaces.
Home-page: https://loicvh.gitlab.io/quadproj
Author: Loïc Van Hoorebeeck
Author-email: loic_quadproj@loicvh.eu
Project-URL: Bug Tracker, https://gitlab.com/loicvh/quadproj/issues
Project-URL: Documentation, https://loicvh.gitlab.io/quadproj
Project-URL: Source Code, https://gitlab.com/loicvh/quadproj
Classifier: Programming Language :: Python :: 3
Classifier: License :: OSI Approved :: MIT License
Classifier: Operating System :: OS Independent
Requires-Python: >=3.6
License-File: LICENSE
